pybotter/__init__.py
pybotter/bothandler.py
pybotter/pybotter.py
pybotter/soundhandler.py
pybotter/vision.py
pybotter/windowhandler.py
pybotter/sound/exit.mp3
pybotter/sound/pause.mp3
pybotter/sound/start.mp3
pybotter/sound/unpause.mp3
pybotter/template/template.py
pybotter-0.1.1.dist-info/LICENSE
pybotter-0.1.1.dist-info/METADATA
pybotter-0.1.1.dist-info/WHEEL
pybotter-0.1.1.dist-info/top_level.txt
pybotter-0.1.1.dist-info/RECORD
