Metadata-Version: 2.1
Name: pybotter
Version: 0.1.1
Summary: This module is for doing automation tasks on Windows 10 or above
Home-page: https://github.com/s3794510/pybotter
Author: Cedrus Z Maize
Author-email: servant@theecee.dev
Keywords: python,opencv,mouse,keyboard,automation
Classifier: Development Status :: 1 - Planning
Classifier: Programming Language :: Python :: 2
Classifier: Programming Language :: Python :: 3
Classifier: Operating System :: Microsoft :: Windows :: Windows 10
Requires-Python: <3.12,>=3.0
License-File: LICENSE
Requires-Dist: pywin32 (>=227)
Requires-Dist: numpy (>=1.19)
Requires-Dist: opencv-contrib-python (>=4.5)
Requires-Dist: keyboard (>=0.13)
